coupa_async_client/__init__.py
coupa_async_client/auth.py
coupa_async_client/client.py
coupa_async_client/errors.py
coupa_async_client/py.typed
coupa_async_client/sync_client.py
coupa_async_client/types.py
coupa_async_client-0.1.0.dist-info/METADATA
coupa_async_client-0.1.0.dist-info/WHEEL
coupa_async_client-0.1.0.dist-info/RECORD
