Metadata-Version: 2.4
Name: coupa-async-client
Version: 0.1.0
Summary: Minimal async Coupa client with offset pagination, concurrency, and retries.
Project-URL: Repository, https://github.com/RodrigoMufatto/coupa_async_client
Author-email: Rodrigo Mufatto <rodrigom3317@gmail.com>
License: MIT
Keywords: api,async,client,coupa,httpx,pagination
Classifier: License :: OSI Approved :: MIT License
Classifier: Programming Language :: Python :: 3
Classifier: Programming Language :: Python :: 3 :: Only
Classifier: Programming Language :: Python :: 3.10
Classifier: Programming Language :: Python :: 3.11
Classifier: Programming Language :: Python :: 3.12
Classifier: Typing :: Typed
Requires-Python: >=3.10
Requires-Dist: httpx>=0.27.0
Requires-Dist: tenacity>=8.3.0
